vantiqconnectorsdk.py
vantiqconnectorsdk-1.3.6.dist-info/licenses/LICENSE
vantiqconnectorsdk-1.3.6.dist-info/METADATA
vantiqconnectorsdk-1.3.6.dist-info/WHEEL
vantiqconnectorsdk-1.3.6.dist-info/top_level.txt
vantiqconnectorsdk-1.3.6.dist-info/RECORD
