Metadata-Version: 2.4
Name: vantiqconnectorsdk
Version: 1.3.6
Summary: SDK for building Vantiq extension sources/connectors in Python
Home-page: https://github.com/Vantiq/vantiq-extension-sources
Author: Vantiq, Inc
Author-email: fcarter@vantiq.com
License: MIT
Classifier: License :: OSI Approved :: MIT License
Classifier: Programming Language :: Python :: 3.10
Classifier: Programming Language :: Python :: 3.11
Classifier: Programming Language :: Python :: 3.12
Requires-Python: >=3.10
License-File: LICENSE
Requires-Dist: websockets>=11.0.3
Requires-Dist: jprops>=2.0.2
Dynamic: license-file
